MANIFEST.in
setup.py
androwarn/COPYING
androwarn/COPYING.LESSER
androwarn/README.md
androwarn/__init__.py
androwarn/androwarn.py
androwarn/requirements.txt
androwarn.egg-info/PKG-INFO
androwarn.egg-info/SOURCES.txt
androwarn.egg-info/dependency_links.txt
androwarn.egg-info/entry_points.txt
androwarn.egg-info/requires.txt
androwarn.egg-info/top_level.txt
androwarn/_SampleApplication/AndroidManifest.xml
androwarn/_SampleApplication/build.properties
androwarn/_SampleApplication/build.xml
androwarn/_SampleApplication/default.properties
androwarn/_SampleApplication/local.properties
androwarn/_SampleApplication/proguard.cfg
androwarn/_SampleApplication/bin/SampleApplication.apk
androwarn/_SampleApplication/bin/classes.dex
androwarn/_SampleApplication/bin/classes/com/androwarn/sampleapplication/BusterReceiver.class
androwarn/_SampleApplication/bin/classes/com/androwarn/sampleapplication/NativeCode.class
androwarn/_SampleApplication/bin/classes/com/androwarn/sampleapplication/R$attr.class
androwarn/_SampleApplication/bin/classes/com/androwarn/sampleapplication/R$layout.class
androwarn/_SampleApplication/bin/classes/com/androwarn/sampleapplication/R$string.class
androwarn/_SampleApplication/bin/classes/com/androwarn/sampleapplication/R.class
androwarn/_SampleApplication/bin/classes/com/androwarn/sampleapplication/SampleApplication.class
androwarn/_SampleApplication/gen/com/androwarn/sampleapplication/R.java
androwarn/_SampleApplication/jni/Android.mk
androwarn/_SampleApplication/jni/Application.mk
androwarn/_SampleApplication/jni/nativecode.c
androwarn/_SampleApplication/jni/nativecode.h
androwarn/_SampleApplication/obj/local/armeabi/objs/nativecode/nativecode.o
androwarn/_SampleApplication/obj/local/armeabi/objs/nativecode/nativecode.o.d
androwarn/_SampleApplication/obj/local/x86/objs/nativecode/nativecode.o
androwarn/_SampleApplication/obj/local/x86/objs/nativecode/nativecode.o.d
androwarn/_SampleApplication/res/layout/main.xml
androwarn/_SampleApplication/res/values/strings.xml
androwarn/_SampleApplication/src/com/androwarn/sampleapplication/BusterReceiver.java
androwarn/_SampleApplication/src/com/androwarn/sampleapplication/NativeCode.java
