Metadata-Version: 2.1
Name: androwarn
Version: 1.6
Summary: Yet another static code analyzer for malicious Android applications
Home-page: https://github.com/maaaaz/androwarn
Author: Thomas D.
Author-email: tdebize@mail.com
License: LGPL
Keywords: androwarn android apk dalvik static malicious behaviours behaviors reverse disassemble
Platform: UNKNOWN
Classifier: Topic :: Security
Classifier: Development Status :: 5 - Production/Stable
Classifier: Intended Audience :: Information Technology
Classifier: License :: OSI Approved :: GNU Library or Lesser General Public License (LGPL)
Requires-Python: >=2.7
